azure/ai/contentunderstanding/__init__.py
azure/ai/contentunderstanding/_client.py
azure/ai/contentunderstanding/_configuration.py
azure/ai/contentunderstanding/_patch.py
azure/ai/contentunderstanding/_validation.py
azure/ai/contentunderstanding/_version.py
azure/ai/contentunderstanding/py.typed
azure/ai/contentunderstanding/_operations/__init__.py
azure/ai/contentunderstanding/_operations/_operations.py
azure/ai/contentunderstanding/_operations/_patch.py
azure/ai/contentunderstanding/_utils/__init__.py
azure/ai/contentunderstanding/_utils/model_base.py
azure/ai/contentunderstanding/_utils/serialization.py
azure/ai/contentunderstanding/_utils/utils.py
azure/ai/contentunderstanding/aio/__init__.py
azure/ai/contentunderstanding/aio/_client.py
azure/ai/contentunderstanding/aio/_configuration.py
azure/ai/contentunderstanding/aio/_patch.py
azure/ai/contentunderstanding/aio/_operations/__init__.py
azure/ai/contentunderstanding/aio/_operations/_operations.py
azure/ai/contentunderstanding/aio/_operations/_patch.py
azure/ai/contentunderstanding/aio/models/__init__.py
azure/ai/contentunderstanding/aio/models/_patch.py
azure/ai/contentunderstanding/aio/operations/_patch.py
azure/ai/contentunderstanding/models/__init__.py
azure/ai/contentunderstanding/models/_enums.py
azure/ai/contentunderstanding/models/_models.py
azure/ai/contentunderstanding/models/_models.pyi
azure/ai/contentunderstanding/models/_patch.py
azure/ai/contentunderstanding/operations/_patch.py
azure_ai_contentunderstanding-1.0.0b1.dist-info/licenses/LICENSE
azure_ai_contentunderstanding-1.0.0b1.dist-info/METADATA
azure_ai_contentunderstanding-1.0.0b1.dist-info/WHEEL
azure_ai_contentunderstanding-1.0.0b1.dist-info/top_level.txt
azure_ai_contentunderstanding-1.0.0b1.dist-info/RECORD
